indiepixel/__init__.py
indiepixel/cli.py
indiepixel/py.typed
indiepixel/fonts/10x20.bdf
indiepixel/fonts/10x20.pbm
indiepixel/fonts/10x20.pil
indiepixel/fonts/5x8.bdf
indiepixel/fonts/5x8.pbm
indiepixel/fonts/5x8.pil
indiepixel/fonts/6x10-rounded.bdf
indiepixel/fonts/6x10-rounded.pbm
indiepixel/fonts/6x10-rounded.pil
indiepixel/fonts/6x10.bdf
indiepixel/fonts/6x10.pbm
indiepixel/fonts/6x10.pil
indiepixel/fonts/6x13.bdf
indiepixel/fonts/6x13.pbm
indiepixel/fonts/6x13.pil
indiepixel/fonts/CG-pixel-3x5-mono.bdf
indiepixel/fonts/CG-pixel-3x5-mono.pbm
indiepixel/fonts/CG-pixel-3x5-mono.pil
indiepixel/fonts/CG-pixel-4x5-mono.bdf
indiepixel/fonts/CG-pixel-4x5-mono.pbm
indiepixel/fonts/CG-pixel-4x5-mono.pil
indiepixel/fonts/Dina_r400-6.bdf
indiepixel/fonts/Dina_r400-6.pbm
indiepixel/fonts/Dina_r400-6.pil
indiepixel/fonts/slkscr.bdf
indiepixel/fonts/slkscr.pbm
indiepixel/fonts/slkscr.pil
indiepixel/fonts/slkscr.ttf
indiepixel/fonts/slkscrb.ttf
indiepixel/fonts/tb-8.bdf
indiepixel/fonts/tb-8.pbm
indiepixel/fonts/tb-8.pil
indiepixel/fonts/tom-thumb.bdf
indiepixel/fonts/tom-thumb.pbm
indiepixel/fonts/tom-thumb.pil
indiepixel/static/mask.png
indiepixel/static/screen.css
indiepixel/templates/base.html
indiepixel/templates/index.html
indiepixel/templates/widget.html
indiepixel-0.8.6.dist-info/METADATA
indiepixel-0.8.6.dist-info/WHEEL
indiepixel-0.8.6.dist-info/entry_points.txt
indiepixel-0.8.6.dist-info/RECORD
