Metadata-Version: 2.4
Name: indiepixel
Version: 0.8.6
Summary: Generate pixel graphics for the Tidbyt
Project-URL: Homepage, https://github.com/tmcw/indiepixel
Project-URL: Issues, https://github.com/tmcw/indiepixel/issues
Author-email: Tom MacWright <tom@macwright.com>
Classifier: License :: OSI Approved :: MIT License
Classifier: Operating System :: OS Independent
Classifier: Programming Language :: Python :: 3
Classifier: Programming Language :: Python :: 3.12
Classifier: Programming Language :: Python :: 3.13
Requires-Python: >=3.12
Requires-Dist: click>=8.1.7
Requires-Dist: flask>=3.1.0
Requires-Dist: pillow>=11.0.0
